detidelevel/__init__.py
detidelevel/core.py
detidelevel/plot.py
detidelevel/util.py
detidelevel/datasets/__init__.py
detidelevel/tests/__init__.py
detidelevel/tests/test_detide.py
detidelevel-1.0.5.dist-info/METADATA
detidelevel-1.0.5.dist-info/WHEEL
detidelevel-1.0.5.dist-info/licenses/LICENSE.txt
detidelevel-1.0.5.dist-info/RECORD
