Metadata-Version: 2.3
Name: detidelevel
Version: 1.0.5
Summary: Functions to remove tidal signals from surface water levels
Project-URL: Homepage, https://github.com/mullenkamp/detidelevel
Author-email: Mike Kittridge <mullenkamp1@gmail.com>
License: Apache-2.0
Keywords: level,tide
Classifier: Development Status :: 3 - Alpha
Classifier: Intended Audience :: Developers
Classifier: License :: OSI Approved :: Apache Software License
Classifier: Programming Language :: Python :: 2
Classifier: Programming Language :: Python :: 2.7
Classifier: Programming Language :: Python :: 3
Classifier: Programming Language :: Python :: 3.4
Classifier: Programming Language :: Python :: 3.5
Classifier: Programming Language :: Python :: 3.6
Classifier: Topic :: Software Development :: Build Tools
Requires-Python: >=3.8
Requires-Dist: pandas
Requires-Dist: statsmodels
